<annotation verified="yes">
    <folder>Annotation</folder>
    <filename>Funny-Sheep-1068x623.jpg</filename>
    <path>Sheeps-PascalVOC-export/Annotations/Funny-Sheep-1068x623.jpg</path>
    <source>
        <database>Unknown</database>
    </source>
    <size>
        <width>1068</width>
        <height>623</height>
        <depth>3</depth>
    </size>
    <segmented>0</segmented>
    <object>
    <name>sheep</name>
    <pose>Unspecified</pose>
    <truncated>0</truncated>
    <difficult>0</difficult>
    <bndbox>
        <xmin>1</xmin>
        <ymin>23</ymin>
        <xmax>982</xmax>
        <ymax>623</ymax>
    </bndbox>
</object>
</annotation>
